{".class": "MypyFile", "_fullname": "automata", "is_partial_stub_package": false, "is_stub": false, "names": {".class": "SymbolTable", "Automata": {".class": "SymbolTableNode", "kind": "Gdef", "node": {".class": "TypeInfo", "_promote": null, "abstract_attributes": [], "bases": ["builtins.object"], "declared_metaclass": null, "defn": {".class": "ClassDef", "fullname": "automata.Automata", "name": "Automata", "type_vars": []}, "flags": [], "fullname": "automata.Automata", "metaclass_type": null, "metadata": {}, "module_name": "automata", "mro": ["automata.Automata", "builtins.object"], "names": {".class": "SymbolTable", "__init__": {".class": "SymbolTableNode", "kind": "Mdef", "node": {".class": "FuncDef", "arg_kinds": [0, 0, 0, 0, 0], "arg_names": ["self", "rule", "radix", "limit", "phrase"], "flags": [], "fullname": "automata.Automata.__init__", "name": "__init__", "type": null}}, "get_next_phrase": {".class": "SymbolTableNode", "kind": "Mdef", "node": {".class": "FuncDef", "arg_kinds": [0, 0], "arg_names": ["self", "current_phrase"], "flags": [], "fullname": "automata.Automata.get_next_phrase", "name": "get_next_phrase", "type": null}}, "get_next_state": {".class": "SymbolTableNode", "kind": "Mdef", "node": {".class": "FuncDef", "arg_kinds": [0, 0, 0, 0], "arg_names": ["self", "ladj", "act", "radj"], "flags": [], "fullname": "automata.Automata.get_next_state", "name": "get_next_state", "type": null}}, "init_automata": {".class": "SymbolTableNode", "kind": "Mdef", "node": {".class": "FuncDef", "arg_kinds": [0], "arg_names": ["self"], "flags": [], "fullname": "automata.Automata.init_automata", "name": "init_automata", "type": null}}, "limit": {".class": "SymbolTableNode", "implicit": true, "kind": "Mdef", "node": {".class": "Var", "flags": [], "fullname": "automata.Automata.limit", "name": "limit", "type": {".class": "AnyType", "missing_import_name": null, "source_any": null, "type_of_any": 1}}}, "phrase": {".class": "SymbolTableNode", "implicit": true, "kind": "Mdef", "node": {".class": "Var", "flags": [], "fullname": "automata.Automata.phrase", "name": "phrase", "type": {".class": "AnyType", "missing_import_name": null, "source_any": null, "type_of_any": 1}}}, "radix": {".class": "SymbolTableNode", "implicit": true, "kind": "Mdef", "node": {".class": "Var", "flags": [], "fullname": "automata.Automata.radix", "name": "radix", "type": {".class": "AnyType", "missing_import_name": null, "source_any": null, "type_of_any": 1}}}, "rule": {".class": "SymbolTableNode", "implicit": true, "kind": "Mdef", "node": {".class": "Var", "flags": [], "fullname": "automata.Automata.rule", "name": "rule", "type": {".class": "AnyType", "missing_import_name": null, "source_any": null, "type_of_any": 1}}}, "transitions": {".class": "SymbolTableNode", "implicit": true, "kind": "Mdef", "node": {".class": "Var", "flags": [], "fullname": "automata.Automata.transitions", "name": "transitions", "type": {".class": "AnyType", "missing_import_name": null, "source_any": null, "type_of_any": 1}}}}, "tuple_type": null, "type_vars": [], "typeddict_type": null}}, "__doc__": {".class": "SymbolTableNode", "kind": "Gdef", "node": {".class": "Var", "flags": ["is_ready"], "fullname": "automata.__doc__", "name": "__doc__", "type": "builtins.str"}}, "__file__": {".class": "SymbolTableNode", "kind": "Gdef", "node": {".class": "Var", "flags": ["is_ready"], "fullname": "automata.__file__", "name": "__file__", "type": "builtins.str"}}, "__name__": {".class": "SymbolTableNode", "kind": "Gdef", "node": {".class": "Var", "flags": ["is_ready"], "fullname": "automata.__name__", "name": "__name__", "type": "builtins.str"}}, "__package__": {".class": "SymbolTableNode", "kind": "Gdef", "node": {".class": "Var", "flags": ["is_ready"], "fullname": "automata.__package__", "name": "__package__", "type": "builtins.str"}}, "itertools": {".class": "SymbolTableNode", "cross_ref": "itertools", "kind": "Gdef"}, "random": {".class": "SymbolTableNode", "cross_ref": "random", "kind": "Gdef"}}, "path": "c:\\Users\\pista\\Desktop\\final\\automata.py"}